Workbook

Sheet Data
A1: Name | B1: Portfolio | C1: Ref. Curr. | D1: Market Value Ref. Curr. | E1: Current Value USD | F1: Cash USD | G1: YTD TWRR
A2: Alemagna, Alberto Pietro | B2: 1627998 | C2: EUR | D2: 2825552.1 | E2: 3148920.5 | F2: 2076.2407 | G2: -0.003
A3: Alemagna, Tancredi Luigi | B3: 1619782 | C3: EUR | D3: 2613571.7 | E3: 2912680.1 | F3: 1097.7892 | G3: -0.01
A4: Ancona, Giselda | B4: 1648638 | C4: EUR | D4: 970166.51 | E4: 1081196.5 | F4: 1170.0803 | G4: -0.0114
A5: Bertini, Marco | B5: 112029 | C5: USD | D5: 1545709 | E5: 1545709 | F5: 927.56 | G5: -0.0519
A6: BISVALLES ASSETS INC. | B6: 1649314 | C6: EUR | D6: 9685868.5 | E6: 10794361 | F6: 4336.292 | G6: -0.0121
A7: Bucchioni, Fabio | B7: 1592092 | C7: EUR | D7: 492926.09 | E7: 549338.68 | F7: 1151.3678 | G7: -0.0116
A8: Cariboni, Elisa | B8: 1600379 | C8: EUR | D8: 1284400.3 | E8: 1431392.6 | F8: 1023.4602 | G8: -0.0111
A9: Fariniundici S.p.A. | B9: 1644446 | C9: EUR | D9: 10889122 | E9: 12135320 | F9: 3492.507 | G9: 0.0001
A10: Galli, Federico | B10: 1621661 | C10: EUR | D10: 550025.1 | E10: 612972.34 | F10: 587.24175 | G10: -0.0109
A11: Hera Società Fiduciaria e di revisione S.p.A. - 05250 | B11: 1696403 | C11: EUR | D11: 653903.94 | E11: 728739.53 | F11: 216.07425 | G11: -0.0036
A12: Hera Società Fiduciaria e di revisione S.p.A. - - 05361 | B12: 1706128 | C12: EUR | D12: 1012590.8 | E12: 1128476.1 | F12: 976.51849 | G12: -0.0143
A13: Laruffa, Alessia | B13: 1596151 | C13: EUR | D13: 2324949.6 | E13: 2591026.8 | F13: 47798.443 | G13: -0.0099
... A19: Laruffa, Sergio | B19: 1591822 | C19: USD | D19: 4898103.5 | E19: 4898103.5 | F19: 1656.41 | G19: -0.0529
A20: Lettieri, Riccardo | B20: 1660765 | C20: EUR | D20: -531422.8 | E20: -592241.12 | G20: 0.0264
A21: Lettieri, Riccardo | B21: 1660765 | C21: EUR | D21: 828076.74 | E21: 922845.41 | F21: 1062.8019 | G21: -0.0157
A22: Lettieri, Umberto | B22: 1710712 | C22: USD | D22: 1440819.5 | E22: 1440819.5 | F22: 3121.65 | G22: -0.0095
A23: Malerba, Maria Clara | B23: 1632673 | C23: EUR | D23: -715416.07 | E23: -797291.37 | F23: 698.27737 | G23: 0.0294
A24: Malerba, Maria Clara | B24: 1632673 | C24: EUR | D24: 5260322.4 | E24: 5862336.3 | F24: 1317.6606 | G24: -0.0105
A25: Marchesi, Riccardo | B25: 1592866 | C25: EUR | D25: 1278060.2 | E25: 1424326.9 | F25: 1449.3366 | G25: -0.0099
A26: Minardi, Mario Paolo | B26: 1650579 | C26: EUR | D26: 563035.83 | E26: 627472.08 | F26: 909.19088 | G26: -0.011
A27: Petrassi, Raffaele | B27: 1656189 | C27: EUR | D27: 314579.32 | E27: 350581.13 | F27: 2025.9575 | G27: -0.0094
A28: Saira Holding S.r.L. | B28: 1690341 | C28: EUR | D28: 171764.2 | E28: 191421.64 | F28: 868.63085 | G28: 0.0004
A29: Siciliano, Rosanna | B29: 1597944 | C29: EUR | D29: 1674812.7 | E29: 1866485.5 | F29: 536.23685 | G29: -0.0065
A30: Simon Fiduciaria S.p.A. - POS. FID. 6297 | B30: 1660666 | C30: EUR | D30: 2673094.7 | E30: 2979015.2 | F30: 2749.6251 | G30: -0.001
A31: Simon Fiduciaria S.p.A. - POS. FID. 6297 | B31: 1660666 | C31: EUR | D31: 3766957.6 | E31: 4198064.5 | F31: 5485.0444 | G31: -0.0006
A32: Terenzi, Federico | B32: 1620379 | C32: EUR | D32: 122054.35 | E32: 136022.78 | F32: 16.621509 | G32: -0.0098
A33: Virlinzi, Francesco | B33: 1648903 | C33: EUR | D33: 9267760.9 | E33: 10328403 | F33: 5193.713 | G33: -0.0097

Sheet T bills
A1: Description | B1: ISIN | C1: Name / Symbol | D1: Portfolio | E1: Trading Curr. | F1: Ref. Curr. | G1: Quantity | H1: Maturity | I1: YTM | J1: Cost price | K1: Market price | L1: Exchange rate | M1: Market value | N1: Accrued Interest | O1: Change price | P1: Change total | Q1: % of net assets
A2: 0% Italy Treasury Bills 14.01.2027 Reg-S Senior | B2: IT0005689887 | C2: Petrassi, Raffaele | D2: 1656189 | E2: EUR | F2: EUR | G2: 17000 | H2: 2027-01-13T23:00:00Z | J2: 99.434647 | K2: 99.425 | L2: 1 | M2: 16902.25 | O2: -0.0097019089 | P2: -0.0097019089 | Q2: 5.3729692
A3: 0% Italy Treasury Bills 14.01.2027 Reg-S Senior | B3: IT0005689887 | C3: Laruffa, Sergio | D3: 1591822 | E3: EUR | F3: USD | G3: 5000 | H3: 2027-01-13T23:00:00Z | J3: 99.4346 | K3: 99.425 | L3: 1.1144 | M3: 4971.25 | O3: -0.009654587 | P3: 0.19622631 | Q3: 0.11310867
A4: 0% Italy Treasury Bills 14.01.2027 Reg-S Senior | B4: IT0005689887 | C4: Bucchioni, Fabio | D4: 1592092 | E4: EUR | F4: EUR | G4: 22000 | H4: 2027-01-13T23:00:00Z | J4: 99.434955 | K4: 99.425 | L4: 1 | M4: 21873.5 | O4: -0.010011113 | P4: -0.010011113 | Q4: 4.4374807
A5: 0% Italy Treasury Bills 14.01.2027 Reg-S Senior | B5: IT0005689887 | C5: Alemagna, Alberto Pietro | D5: 1627998 | E5: EUR | F5: EUR | G5: 132000 | H5: 2027-01-13T23:00:00Z | J5: 99.434932 | K5: 99.425 | L5: 1 | M5: 131241 | O5: -0.0099882587 | P5: -0.0099882587 | Q5: 4.6447914
A6: 0% Italy Treasury Bills 14.01.2027 Reg-S Senior | B6: IT0005689887 | C6: Simon Fiduciaria S.p.A. - POS. FID. 6297 | D6: 1660666 | E6: EUR | F6: EUR | G6: 240000 | H6: 2027-01-13T23:00:00Z | J6: 99.373442 | K6: 99.425 | L6: 1 | M6: 238620 | O6: 0.051883413 | P6: 0.051883413 | Q6: 6.3345549
A7: 0% Italy Treasury Bills 14.01.2027 Reg-S Senior | B7: IT0005689887 | C7: Marchesi, Riccardo | D7: 1592866 | E7: EUR | F7: EUR | G7: 58000 | H7: 2027-01-13T23:00:00Z | J7: 99.435172 | K7: 99.425 | L7: 1 | M7: 57666.5 | O7: -0.010230197 | P7: -0.010230197 | Q7: 4.5120332
A8: 0% Italy Treasury Bills 14.01.2027 Reg-S Senior | B8: IT0005689887 | C8: Minardi, Mario Paolo | D8: 1650579 | E8: EUR | F8: EUR | G8: 26000 | H8: 2027-01-13T23:00:00Z | J8: 99.434654 | K8: 99.425 | L8: 1 | M8: 25850.5 | O8: -0.0097087341 | P8: -0.0097087341 | Q8: 4.5912709
A9: 0% Italy Treasury Bills 14.01.2027 Reg-S Senior | B9: IT0005689887 | C9: Cariboni, Elisa | D9: 1600379 | E9: EUR | F9: EUR | G9: 55000 | H9: 2027-01-13T23:00:00Z | J9: 99.435182 | K9: 99.425 | L9: 1 | M9: 54683.75 | O9: -0.010239654 | P9: -0.010239654 | Q9: 4.2575318
A10: 0% Italy Treasury Bills 14.01.2027 Reg-S Senior | B10: IT0005689887 | C10: Laruffa, Sergio | D10: 1591822 | E10: EUR | F10: USD | G10: 49000 | H10: 2027-01-13T23:00:00Z | J10: 99.434653 | K10: 99.425 | L10: 1.1144 | M10: 48718.25 | O10: -0.0097079448 | P10: 0.19613379 | Q10: 63.009419
A11: 0% Italy Treasury Bills 14.01.2027 Reg-S Senior | B11: IT0005689887 | C11: Simon Fiduciaria S.p.A. - POS. FID. 6297 | D11: 1660666 | E11: EUR | F11: EUR | G11: 92000 | H11: 2027-01-13T23:00:00Z | J11: 99.373446 | K11: 99.425 | L11: 1 | M11: 91471 | O11: 0.0518794 | P11: 0.0518794 | Q11: 3.4219139
A12: 0% Italy Treasury Bills 14.01.2027 Reg-S Senior | B12: IT0005689887 | C12: Ancona, Giselda | D12: 1648638 | E12: EUR | F12: EUR | G12: 19000 | H12: 2027-01-13T23:00:00Z | J12: 99.434474 | K12: 99.425 | L12: 1 | M12: 18890.75 | O12: -0.0095275651 | P12: -0.0095275651 | Q12: 1.9471657
A13: 0% Italy Treasury Bills 14.01.2027 Reg-S Senior | B13: IT0005689887 | C13: Galli, Federico | D13: 1621661 | E13: EUR | F13: EUR | G13: 26000 | H13: 2027-01-13T23:00:00Z | J13: 99.434692 | K13: 99.425 | L13: 1 | M13: 25850.5 | O13: -0.0097474106 | P13: -0.0097474106 | Q13: 4.6998764
... A40: 0% United States Treasury Bills 25.03.2027 Senior | B40: US912797WL77 | C40: Lettieri, Umberto | D40: 1710712 | E40: USD | F40: USD | G40: 38300 | H40: 2027-03-24T23:00:00Z | J40: 97.913864 | K40: 98.3048 | L40: 1 | M40: 37650.74 | O40: 0.39926925 | P40: 0.39926925 | Q40: 2.6131476
A41: 2.85% Italy Treasury Bonds 01.02.2031 Senior | B41: IT0005671273 | C41: Petrassi, Raffaele | D41: 1656189 | E41: EUR | F41: EUR | G41: 9000 | H41: 2031-01-31T23:00:00Z | I41: 0.039569656 | J41: 99.052444 | K41: 95.97 | L41: 1 | M41: 8698.64 | N41: 61.34 | O41: -3.1119317 | P41: -3.1119317 | Q41: 2.7651659
A42: 2.85% Italy Treasury Bonds 01.02.2031 Senior | B42: IT0005671273 | C42: Laruffa, Sergio | D42: 1591822 | E42: EUR | F42: USD | G42: 50000 | H42: 2031-01-31T23:00:00Z | I42: 0.039569656 | J42: 99.05248 | K42: 95.97 | L42: 1.1144 | M42: 48325.76 | N42: 340.76 | O42: -3.1119665 | P42: -6.744567 | Q42: 1.0995352
A43: 2.85% Italy Treasury Bonds 01.02.2031 Senior | B43: IT0005671273 | C43: Bucchioni, Fabio | D43: 1592092 | E43: EUR | F43: EUR | G43: 15000 | H43: 2031-01-31T23:00:00Z | I43: 0.039569656 | J43: 99.060467 | K43: 95.97 | L43: 1 | M43: 14497.73 | N43: 102.23 | O43: -3.119778 | P43: -3.119778 | Q43: 2.941157
A44: 2.85% Italy Treasury Bonds 01.02.2031 Senior | B44: IT0005671273 | C44: Alemagna, Alberto Pietro | D44: 1627998 | E44: EUR | F44: EUR | G44: 85000 | H44: 2031-01-31T23:00:00Z | I44: 0.039569656 | J44: 99.055494 | K44: 95.97 | L44: 1 | M44: 82153.79 | N44: 579.29 | O44: -3.1149147 | P44: -3.1149147 | Q44: 2.9075305
A45: 2.85% Italy Treasury Bonds 01.02.2031 Senior | B45: IT0005671273 | C45: Simon Fiduciaria S.p.A. - POS. FID. 6297 | D45: 1660666 | E45: EUR | F45: EUR | G45: 111000 | H45: 2031-01-31T23:00:00Z | I45: 0.039569656 | J45: 99.063 | K45: 95.97 | L45: 1 | M45: 107283.19 | N45: 756.49 | O45: -3.1222555 | P45: -3.1222555 | Q45: 2.8480063
A46: 2.85% Italy Treasury Bonds 01.02.2031 Senior | B46: IT0005671273 | C46: Marchesi, Riccardo | D46: 1592866 | E46: EUR | F46: EUR | G46: 38000 | H46: 2031-01-31T23:00:00Z | I46: 0.039569656 | J46: 99.0555 | K46: 95.97 | L46: 1 | M46: 36727.58 | N46: 258.98 | O46: -3.1149204 | P46: -3.1149204 | Q46: 2.8736972
A47: 2.85% Italy Treasury Bonds 01.02.2031 Senior | B47: IT0005671273 | C47: Saira Holding S.r.L. | D47: 1690341 | E47: EUR | F47: EUR | G47: 5000 | H47: 2031-01-31T23:00:00Z | I47: 0.039569656 | J47: 99.055 | K47: 95.97 | L47: 1 | M47: 4832.58 | N47: 34.08 | O47: -3.1144314 | P47: -3.1144314 | Q47: 2.8134966
A48: 2.85% Italy Treasury Bonds 01.02.2031 Senior | B48: IT0005671273 | C48: Minardi, Mario Paolo | D48: 1650579 | E48: EUR | F48: EUR | G48: 17000 | H48: 2031-01-31T23:00:00Z | I48: 0.039569656 | J48: 99.052471 | K48: 95.97 | L48: 1 | M48: 16430.76 | N48: 115.86 | O48: -3.1119573 | P48: -3.1119573 | Q48: 2.9182441
A49: 2.85% Italy Treasury Bonds 01.02.2031 Senior | B49: IT0005671273 | C49: Cariboni, Elisa | D49: 1600379 | E49: EUR | F49: EUR | G49: 38000 | H49: 2031-01-31T23:00:00Z | I49: 0.039569656 | J49: 99.0605 | K49: 95.97 | L49: 1 | M49: 36727.58 | N49: 258.98 | O49: -3.1198106 | P49: -3.1198106 | Q49: 2.859512
A50: 2.85% Italy Treasury Bonds 01.02.2031 Senior | B50: IT0005671273 | C50: Alemagna, Tancredi Luigi | D50: 1619782 | E50: EUR | F50: EUR | G50: 84000 | H50: 2031-01-31T23:00:00Z | I50: 0.039569656 | J50: 99.060488 | K50: 95.97 | L50: 1 | M50: 81187.28 | N50: 572.48 | O50: -3.119799 | P50: -3.119799 | Q50: 3.1063728
A51: 2.85% Italy Treasury Bonds 01.02.2031 Senior | B51: IT0005671273 | C51: Simon Fiduciaria S.p.A. - POS. FID. 6297 | D51: 1660666 | E51: EUR | F51: EUR | G51: 81000 | H51: 2031-01-31T23:00:00Z | I51: 0.039569656 | J51: 99.063 | K51: 95.97 | L51: 1 | M51: 78287.73 | N51: 552.03 | O51: -3.1222555 | P51: -3.1222555 | Q51: 2.9287301
A52: 2.85% Italy Treasury Bonds 01.02.2031 Senior | B52: IT0005671273 | C52: Fariniundici S.p.A. | D52: 1644446 | E52: EUR | F52: EUR | G52: 330000 | H52: 2031-01-31T23:00:00Z | I52: 0.039569656 | J52: 99.063 | K52: 95.97 | L52: 1 | M52: 318950.02 | N52: 2249.02 | O52: -3.1222555 | P52: -3.1222555 | Q52: 2.9290702
... A460: 4.75% United States Treasury Notes 30.09.2028 Senior | B460: US91282CRP85 | C460: Hera Società Fiduciaria e di revisione S.p.A. - - 05361 | D460: 1706128 | E460: USD | F460: EUR | G460: 22500 | H460: 2028-09-29T22:00:00Z | I460: 0.04722 | J460: 99.6992 | K460: 100.03 | L460: 1.1144 | M460: 22588.96 | N460: 82.21 | O460: 0.33179805 | P460: 2.2591146 | Q460: 2.0017227
A461: iShares $ Treasury Bond 20+yr UCITS ETF EUR H D | B461: IE00BD8PGZ49 | C461: Fariniundici S.p.A. | D461: 1644446 | E461: EUR | F461: EUR | G461: 295535 | J461: 3.3422183 | K461: 2.67075 | L461: 1 | M461: 789300.1 | O461: -20.090498 | P461: -20.090498 | Q461: 7.2485193

Sheet Summary
E3: EUR/USD | F3: 1.1144
E4: Shares Edge MSCI World Momentum Factor UCITS ETF | F4: Price | G4: Units | H4: Value | K4: The VanEck Semiconductor UCITS ETF | L4: Price | M4: Units | N4: Value | Q4: Cash (USD)
E5: IE00BP3QZ825 | F5: 111.08 | K5: IE00BMC38736 | L5: 100.04
A6: Client | B6: Portfolio | C6: Ref. Curr. | D6: Units | I6: % of Portfolio | J6: Units | O6: % of Portfolio | Q6: Naked Cash (USD) | R6: US T-bills (USD) | S6: EUR T-bills (USD) | T6: Total Cash (USD)
A7: TOTAL | D7: =SUM(D8:D35) | G7: =SUM(G8:G35) | H7: =SUM(H8:H35) | I7: {=IFERROR(H7/SUMPRODUCT(SUMIFS(Data!$E:$E,Data!$B:$B,$B$8:$B$35)),0)} | J7: =SUM(J8:J35) | M7: =SUM(M8:M35) | N7: =SUM(N8:N35) | O7: {=IFERROR(N7/SUMPRODUCT(SUMIFS(Data!$E:$E,Data!$B:$B,$B$8:$B$35)),0)} | Q7: =SUM(Q8:Q35) | R7: =SUM(R8:R35) | S7: =SUM(S8:S35) | T7: =SUM(T8:T35)
A8: Balanced
A9: Bertini, Marco | B9: 112029 | C9: USD | D9: =SUMIFS(#REF!,#REF!,$B9,#REF!,#REF!) | G9: =#REF!/$F$5 | H9: =MROUND(G9,1)*$F$5 | I9: =IFERROR(H9/INDEX(Data!$E:$E,MATCH($B9,Data!$B:$B,0)),0) | J9: =SUMIFS(#REF!,#REF!,$B9,#REF!,#REF!) | K9: =#REF! | M9: =#REF!/$L$5 | N9: =MROUND(M9,1)*$L$5 | O9: =IFERROR(N9/INDEX(Data!$E:$E,MATCH($B9,Data!$B:$B,0)),0) | Q9: =IFERROR(INDEX(Data!$F:$F,MATCH($B9,Data!$B:$B,0)),0) | R9: =SUMIFS('T bills'!$M:$M,'T bills'!$D:$D,$B9,'T bills'!$E:$E,"USD",'T bills'!$A:$A,"*Treasury Bills*") | S9: =SUMIFS('T bills'!$M:$M,'T bills'!$D:$D,$B9,'T bills'!$E:$E,"EUR",'T bills'!$A:$A,"*Treasury Bills*")*$F$3 | T9: =SUM(Q9:S9)
A10: Laruffa, Alessia | B10: 1596151 | C10: EUR | D10: =SUMIFS(#REF!,#REF!,$B10,#REF!,#REF!) | G10: =#REF!/$F$5 | H10: =MROUND(G10,1)*$F$5 | I10: =IFERROR(H10/INDEX(Data!$E:$E,MATCH($B10,Data!$B:$B,0)),0) | J10: =SUMIFS(#REF!,#REF!,$B10,#REF!,#REF!) | K10: =#REF! | M10: =#REF!/$L$5 | N10: =MROUND(M10,1)*$L$5 | O10: =IFERROR(N10/INDEX(Data!$E:$E,MATCH($B10,Data!$B:$B,0)),0) | Q10: =IFERROR(INDEX(Data!$F:$F,MATCH($B10,Data!$B:$B,0)),0) | R10: =SUMIFS('T bills'!$M:$M,'T bills'!$D:$D,$B10,'T bills'!$E:$E,"USD",'T bills'!$A:$A,"*Treasury Bills*") | S10: =SUMIFS('T bills'!$M:$M,'T bills'!$D:$D,$B10,'T bills'!$E:$E,"EUR",'T bills'!$A:$A,"*Treasury Bills*")*$F$3 | T10: =SUM(Q10:S10)
A11: Laruffa, Serena | B11: 1596193 | C11: EUR | D11: =SUMIFS(#REF!,#REF!,$B11,#REF!,#REF!) | G11: =#REF!/$F$5 | H11: =MROUND(G11,1)*$F$5 | I11: =IFERROR(H11/INDEX(Data!$E:$E,MATCH($B11,Data!$B:$B,0)),0) | J11: =SUMIFS(#REF!,#REF!,$B11,#REF!,#REF!) | K11: =#REF! | M11: =#REF!/$L$5 | N11: =MROUND(M11,1)*$L$5 | O11: =IFERROR(N11/INDEX(Data!$E:$E,MATCH($B11,Data!$B:$B,0)),0) | Q11: =IFERROR(INDEX(Data!$F:$F,MATCH($B11,Data!$B:$B,0)),0) | R11: =SUMIFS('T bills'!$M:$M,'T bills'!$D:$D,$B11,'T bills'!$E:$E,"USD",'T bills'!$A:$A,"*Treasury Bills*") | S11: =SUMIFS('T bills'!$M:$M,'T bills'!$D:$D,$B11,'T bills'!$E:$E,"EUR",'T bills'!$A:$A,"*Treasury Bills*")*$F$3 | T11: =SUM(Q11:S11)
A12: Siciliano, Rosanna | B12: 1597944 | C12: EUR | D12: =SUMIFS(#REF!,#REF!,$B12,#REF!,#REF!) | G12: =#REF!/$F$5 | H12: =MROUND(G12,1)*$F$5 | I12: =IFERROR(H12/INDEX(Data!$E:$E,MATCH($B12,Data!$B:$B,0)),0) | J12: =SUMIFS(#REF!,#REF!,$B12,#REF!,#REF!) | K12: =#REF! | M12: =#REF!/$L$5 | N12: =MROUND(M12,1)*$L$5 | O12: =IFERROR(N12/INDEX(Data!$E:$E,MATCH($B12,Data!$B:$B,0)),0) | Q12: =IFERROR(INDEX(Data!$F:$F,MATCH($B12,Data!$B:$B,0)),0) | R12: =SUMIFS('T bills'!$M:$M,'T bills'!$D:$D,$B12,'T bills'!$E:$E,"USD",'T bills'!$A:$A,"*Treasury Bills*") | S12: =SUMIFS('T bills'!$M:$M,'T bills'!$D:$D,$B12,'T bills'!$E:$E,"EUR",'T bills'!$A:$A,"*Treasury Bills*")*$F$3 | T12: =SUM(Q12:S12)
A13: Ancona, Giselda | B13: 1648638 | C13: EUR | D13: =SUMIFS(#REF!,#REF!,$B13,#REF!,#REF!) | G13: =#REF!/$F$5 | H13: =MROUND(G13,1)*$F$5 | I13: =IFERROR(H13/INDEX(Data!$E:$E,MATCH($B13,Data!$B:$B,0)),0) | J13: =SUMIFS(#REF!,#REF!,$B13,#REF!,#REF!) | K13: =#REF! | M13: =#REF!/$L$5 | N13: =MROUND(M13,1)*$L$5 | O13: =IFERROR(N13/INDEX(Data!$E:$E,MATCH($B13,Data!$B:$B,0)),0) | Q13: =IFERROR(INDEX(Data!$F:$F,MATCH($B13,Data!$B:$B,0)),0) | R13: =SUMIFS('T bills'!$M:$M,'T bills'!$D:$D,$B13,'T bills'!$E:$E,"USD",'T bills'!$A:$A,"*Treasury Bills*") | S13: =SUMIFS('T bills'!$M:$M,'T bills'!$D:$D,$B13,'T bills'!$E:$E,"EUR",'T bills'!$A:$A,"*Treasury Bills*")*$F$3 | T13: =SUM(Q13:S13)
A14: Minardi, Mario Paolo | B14: 1650579 | C14: EUR | D14: =SUMIFS(#REF!,#REF!,$B14,#REF!,#REF!) | G14: =#REF!/$F$5 | H14: =MROUND(G14,1)*$F$5 | I14: =IFERROR(H14/INDEX(Data!$E:$E,MATCH($B14,Data!$B:$B,0)),0) | J14: =SUMIFS(#REF!,#REF!,$B14,#REF!,#REF!) | K14: =#REF! | M14: =#REF!/$L$5 | N14: =MROUND(M14,1)*$L$5 | O14: =IFERROR(N14/INDEX(Data!$E:$E,MATCH($B14,Data!$B:$B,0)),0) | Q14: =IFERROR(INDEX(Data!$F:$F,MATCH($B14,Data!$B:$B,0)),0) | R14: =SUMIFS('T bills'!$M:$M,'T bills'!$D:$D,$B14,'T bills'!$E:$E,"USD",'T bills'!$A:$A,"*Treasury Bills*") | S14: =SUMIFS('T bills'!$M:$M,'T bills'!$D:$D,$B14,'T bills'!$E:$E,"EUR",'T bills'!$A:$A,"*Treasury Bills*")*$F$3 | T14: =SUM(Q14:S14)
A15: Marchesi, Riccardo | B15: 1592866 | C15: EUR | D15: =SUMIFS(#REF!,#REF!,$B15,#REF!,#REF!) | G15: =#REF!/$F$5 | H15: =MROUND(G15,1)*$F$5 | I15: =IFERROR(H15/INDEX(Data!$E:$E,MATCH($B15,Data!$B:$B,0)),0) | J15: =SUMIFS(#REF!,#REF!,$B15,#REF!,#REF!) | K15: =#REF! | M15: =#REF!/$L$5 | N15: =MROUND(M15,1)*$L$5 | O15: =IFERROR(N15/INDEX(Data!$E:$E,MATCH($B15,Data!$B:$B,0)),0) | Q15: =IFERROR(INDEX(Data!$F:$F,MATCH($B15,Data!$B:$B,0)),0) | R15: =SUMIFS('T bills'!$M:$M,'T bills'!$D:$D,$B15,'T bills'!$E:$E,"USD",'T bills'!$A:$A,"*Treasury Bills*") | S15: =SUMIFS('T bills'!$M:$M,'T bills'!$D:$D,$B15,'T bills'!$E:$E,"EUR",'T bills'!$A:$A,"*Treasury Bills*")*$F$3 | T15: =SUM(Q15:S15)
A16: Cariboni, Elisa | B16: 1600379 | C16: EUR | D16: =SUMIFS(#REF!,#REF!,$B16,#REF!,#REF!) | G16: =#REF!/$F$5 | H16: =MROUND(G16,1)*$F$5 | I16: =IFERROR(H16/INDEX(Data!$E:$E,MATCH($B16,Data!$B:$B,0)),0) | J16: =SUMIFS(#REF!,#REF!,$B16,#REF!,#REF!) | K16: =#REF! | M16: =#REF!/$L$5 | N16: =MROUND(M16,1)*$L$5 | O16: =IFERROR(N16/INDEX(Data!$E:$E,MATCH($B16,Data!$B:$B,0)),0) | Q16: =IFERROR(INDEX(Data!$F:$F,MATCH($B16,Data!$B:$B,0)),0) | R16: =SUMIFS('T bills'!$M:$M,'T bills'!$D:$D,$B16,'T bills'!$E:$E,"USD",'T bills'!$A:$A,"*Treasury Bills*") | S16: =SUMIFS('T bills'!$M:$M,'T bills'!$D:$D,$B16,'T bills'!$E:$E,"EUR",'T bills'!$A:$A,"*Treasury Bills*")*$F$3 | T16: =SUM(Q16:S16)
A17: Equity
A18: Laruffa, Sergio | B18: 1591822 | C18: USD | D18: =SUMIFS(#REF!,#REF!,$B18,#REF!,#REF!) | G18: =#REF!/$F$5 | H18: =MROUND(G18,1)*$F$5 | I18: =IFERROR(H18/INDEX(Data!$E:$E,MATCH($B18,Data!$B:$B,0)),0) | J18: =SUMIFS(#REF!,#REF!,$B18,#REF!,#REF!) | K18: =#REF! | M18: =#REF!/$L$5 | N18: =MROUND(M18,1)*$L$5 | O18: =IFERROR(N18/INDEX(Data!$E:$E,MATCH($B18,Data!$B:$B,0)),0) | Q18: =IFERROR(INDEX(Data!$F:$F,MATCH($B18,Data!$B:$B,0)),0) | R18: =SUMIFS('T bills'!$M:$M,'T bills'!$D:$D,$B18,'T bills'!$E:$E,"USD",'T bills'!$A:$A,"*Treasury Bills*") | S18: =SUMIFS('T bills'!$M:$M,'T bills'!$D:$D,$B18,'T bills'!$E:$E,"EUR",'T bills'!$A:$A,"*Treasury Bills*")*$F$3 | T18: =SUM(Q18:S18)
A19: Bucchioni, Fabio | B19: 1592092 | C19: EUR | D19: =SUMIFS(#REF!,#REF!,$B19,#REF!,#REF!) | G19: =#REF!/$F$5 | H19: =MROUND(G19,1)*$F$5 | I19: =IFERROR(H19/INDEX(Data!$E:$E,MATCH($B19,Data!$B:$B,0)),0) | J19: =SUMIFS(#REF!,#REF!,$B19,#REF!,#REF!) | K19: =#REF! | M19: =#REF!/$L$5 | N19: =MROUND(M19,1)*$L$5 | O19: =IFERROR(N19/INDEX(Data!$E:$E,MATCH($B19,Data!$B:$B,0)),0) | Q19: =IFERROR(INDEX(Data!$F:$F,MATCH($B19,Data!$B:$B,0)),0) | R19: =SUMIFS('T bills'!$M:$M,'T bills'!$D:$D,$B19,'T bills'!$E:$E,"USD",'T bills'!$A:$A,"*Treasury Bills*") | S19: =SUMIFS('T bills'!$M:$M,'T bills'!$D:$D,$B19,'T bills'!$E:$E,"EUR",'T bills'!$A:$A,"*Treasury Bills*")*$F$3 | T19: =SUM(Q19:S19)
A20: Galli, Federico | B20: 1621661 | C20: EUR | D20: =SUMIFS(#REF!,#REF!,$B20,#REF!,#REF!) | G20: =#REF!/$F$5 | H20: =MROUND(G20,1)*$F$5 | I20: =IFERROR(H20/INDEX(Data!$E:$E,MATCH($B20,Data!$B:$B,0)),0) | J20: =SUMIFS(#REF!,#REF!,$B20,#REF!,#REF!) | K20: =#REF! | M20: =#REF!/$L$5 | N20: =MROUND(M20,1)*$L$5 | O20: =IFERROR(N20/INDEX(Data!$E:$E,MATCH($B20,Data!$B:$B,0)),0) | Q20: =IFERROR(INDEX(Data!$F:$F,MATCH($B20,Data!$B:$B,0)),0) | R20: =SUMIFS('T bills'!$M:$M,'T bills'!$D:$D,$B20,'T bills'!$E:$E,"USD",'T bills'!$A:$A,"*Treasury Bills*") | S20: =SUMIFS('T bills'!$M:$M,'T bills'!$D:$D,$B20,'T bills'!$E:$E,"EUR",'T bills'!$A:$A,"*Treasury Bills*")*$F$3 | T20: =SUM(Q20:S20)
A21: Terenzi, Federico | B21: 1620379 | C21: EUR | D21: =SUMIFS(#REF!,#REF!,$B21,#REF!,#REF!) | G21: =#REF!/$F$5 | H21: =MROUND(G21,1)*$F$5 | I21: =IFERROR(H21/INDEX(Data!$E:$E,MATCH($B21,Data!$B:$B,0)),0) | J21: =SUMIFS(#REF!,#REF!,$B21,#REF!,#REF!) | K21: =#REF! | M21: =#REF!/$L$5 | N21: =MROUND(M21,1)*$L$5 | O21: =IFERROR(N21/INDEX(Data!$E:$E,MATCH($B21,Data!$B:$B,0)),0) | Q21: =IFERROR(INDEX(Data!$F:$F,MATCH($B21,Data!$B:$B,0)),0) | R21: =SUMIFS('T bills'!$M:$M,'T bills'!$D:$D,$B21,'T bills'!$E:$E,"USD",'T bills'!$A:$A,"*Treasury Bills*") | S21: =SUMIFS('T bills'!$M:$M,'T bills'!$D:$D,$B21,'T bills'!$E:$E,"EUR",'T bills'!$A:$A,"*Treasury Bills*")*$F$3 | T21: =SUM(Q21:S21)
A22: Simon Fiduciaria S.p.A. #1 | B22: 1660666 | C22: EUR | D22: =SUMIFS(#REF!,#REF!,$B22,#REF!,#REF!) | G22: =#REF!/$F$5 | H22: =MROUND(G22,1)*$F$5 | I22: =IFERROR(H22/INDEX(Data!$E:$E,MATCH($B22,Data!$B:$B,0)),0) | J22: =SUMIFS(#REF!,#REF!,$B22,#REF!,#REF!) | K22: =#REF! | M22: =#REF!/$L$5 | N22: =MROUND(M22,1)*$L$5 | O22: =IFERROR(N22/INDEX(Data!$E:$E,MATCH($B22,Data!$B:$B,0)),0) | Q22: =IFERROR(INDEX(Data!$F:$F,MATCH($B22,Data!$B:$B,0)),0) | R22: =SUMIFS('T bills'!$M:$M,'T bills'!$D:$D,$B22,'T bills'!$E:$E,"USD",'T bills'!$A:$A,"*Treasury Bills*") | S22: =SUMIFS('T bills'!$M:$M,'T bills'!$D:$D,$B22,'T bills'!$E:$E,"EUR",'T bills'!$A:$A,"*Treasury Bills*")*$F$3 | T22: =SUM(Q22:S22)
A23: Simon Fiduciaria S.p.A. #3 | B23: 1660666 | C23: EUR | D23: =SUMIFS(#REF!,#REF!,$B23,#REF!,#REF!) | G23: =#REF!/$F$5 | H23: =MROUND(G23,1)*$F$5 | I23: =IFERROR(H23/INDEX(Data!$E:$E,MATCH($B23,Data!$B:$B,0)),0) | J23: =SUMIFS(#REF!,#REF!,$B23,#REF!,#REF!) | K23: =#REF! | M23: =#REF!/$L$5 | N23: =MROUND(M23,1)*$L$5 | O23: =IFERROR(N23/INDEX(Data!$E:$E,MATCH($B23,Data!$B:$B,0)),0) | Q23: =IFERROR(INDEX(Data!$F:$F,MATCH($B23,Data!$B:$B,0)),0) | R23: =SUMIFS('T bills'!$M:$M,'T bills'!$D:$D,$B23,'T bills'!$E:$E,"USD",'T bills'!$A:$A,"*Treasury Bills*") | S23: =SUMIFS('T bills'!$M:$M,'T bills'!$D:$D,$B23,'T bills'!$E:$E,"EUR",'T bills'!$A:$A,"*Treasury Bills*")*$F$3 | T23: =SUM(Q23:S23)
A24: Fariniundici S.p.A. | B24: 1644446 | C24: EUR | D24: =SUMIFS(#REF!,#REF!,$B24,#REF!,#REF!) | G24: =#REF!/$F$5 | H24: =MROUND(G24,1)*$F$5 | I24: =IFERROR(H24/INDEX(Data!$E:$E,MATCH($B24,Data!$B:$B,0)),0) | J24: =SUMIFS(#REF!,#REF!,$B24,#REF!,#REF!) | K24: =#REF! | M24: =#REF!/$L$5 | N24: =MROUND(M24,1)*$L$5 | O24: =IFERROR(N24/INDEX(Data!$E:$E,MATCH($B24,Data!$B:$B,0)),0) | Q24: =IFERROR(INDEX(Data!$F:$F,MATCH($B24,Data!$B:$B,0)),0) | R24: =SUMIFS('T bills'!$M:$M,'T bills'!$D:$D,$B24,'T bills'!$E:$E,"USD",'T bills'!$A:$A,"*Treasury Bills*") | S24: =SUMIFS('T bills'!$M:$M,'T bills'!$D:$D,$B24,'T bills'!$E:$E,"EUR",'T bills'!$A:$A,"*Treasury Bills*")*$F$3 | T24: =SUM(Q24:S24)
A25: BISVALLES ASSETS INC. | B25: 1649314 | C25: EUR | D25: =SUMIFS(#REF!,#REF!,$B25,#REF!,#REF!) | G25: =#REF!/$F$5 | H25: =MROUND(G25,1)*$F$5 | I25: =IFERROR(H25/INDEX(Data!$E:$E,MATCH($B25,Data!$B:$B,0)),0) | J25: =SUMIFS(#REF!,#REF!,$B25,#REF!,#REF!) | K25: =#REF! | M25: =#REF!/$L$5 | N25: =MROUND(M25,1)*$L$5 | O25: =IFERROR(N25/INDEX(Data!$E:$E,MATCH($B25,Data!$B:$B,0)),0) | Q25: =IFERROR(INDEX(Data!$F:$F,MATCH($B25,Data!$B:$B,0)),0) | R25: =SUMIFS('T bills'!$M:$M,'T bills'!$D:$D,$B25,'T bills'!$E:$E,"USD",'T bills'!$A:$A,"*Treasury Bills*") | S25: =SUMIFS('T bills'!$M:$M,'T bills'!$D:$D,$B25,'T bills'!$E:$E,"EUR",'T bills'!$A:$A,"*Treasury Bills*")*$F$3 | T25: =SUM(Q25:S25)
A26: Petrassi, Raffaele | B26: 1656189 | C26: EUR | D26: =SUMIFS(#REF!,#REF!,$B26,#REF!,#REF!) | G26: =#REF!/$F$5 | H26: =MROUND(G26,1)*$F$5 | I26: =IFERROR(H26/INDEX(Data!$E:$E,MATCH($B26,Data!$B:$B,0)),0) | J26: =SUMIFS(#REF!,#REF!,$B26,#REF!,#REF!) | K26: =#REF! | M26: =#REF!/$L$5 | N26: =MROUND(M26,1)*$L$5 | O26: =IFERROR(N26/INDEX(Data!$E:$E,MATCH($B26,Data!$B:$B,0)),0) | Q26: =IFERROR(INDEX(Data!$F:$F,MATCH($B26,Data!$B:$B,0)),0) | R26: =SUMIFS('T bills'!$M:$M,'T bills'!$D:$D,$B26,'T bills'!$E:$E,"USD",'T bills'!$A:$A,"*Treasury Bills*") | S26: =SUMIFS('T bills'!$M:$M,'T bills'!$D:$D,$B26,'T bills'!$E:$E,"EUR",'T bills'!$A:$A,"*Treasury Bills*")*$F$3 | T26: =SUM(Q26:S26)
A27: Virlinzi, Francesco | B27: 1648903 | C27: EUR | D27: =SUMIFS(#REF!,#REF!,$B27,#REF!,#REF!) | G27: =#REF!/$F$5 | H27: =MROUND(G27,1)*$F$5 | I27: =IFERROR(H27/INDEX(Data!$E:$E,MATCH($B27,Data!$B:$B,0)),0) | J27: =SUMIFS(#REF!,#REF!,$B27,#REF!,#REF!) | K27: =#REF! | M27: =#REF!/$L$5 | N27: =MROUND(M27,1)*$L$5 | O27: =IFERROR(N27/INDEX(Data!$E:$E,MATCH($B27,Data!$B:$B,0)),0) | Q27: =IFERROR(INDEX(Data!$F:$F,MATCH($B27,Data!$B:$B,0)),0) | R27: =SUMIFS('T bills'!$M:$M,'T bills'!$D:$D,$B27,'T bills'!$E:$E,"USD",'T bills'!$A:$A,"*Treasury Bills*") | S27: =SUMIFS('T bills'!$M:$M,'T bills'!$D:$D,$B27,'T bills'!$E:$E,"EUR",'T bills'!$A:$A,"*Treasury Bills*")*$F$3 | T27: =SUM(Q27:S27)
A28: Alemagna, Alberto Pietro | B28: 1627998 | C28: EUR | D28: =SUMIFS(#REF!,#REF!,$B28,#REF!,#REF!) | G28: =#REF!/$F$5 | H28: =MROUND(G28,1)*$F$5 | I28: =IFERROR(H28/INDEX(Data!$E:$E,MATCH($B28,Data!$B:$B,0)),0) | J28: =SUMIFS(#REF!,#REF!,$B28,#REF!,#REF!) | K28: =#REF! | M28: =#REF!/$L$5 | N28: =MROUND(M28,1)*$L$5 | O28: =IFERROR(N28/INDEX(Data!$E:$E,MATCH($B28,Data!$B:$B,0)),0) | Q28: =IFERROR(INDEX(Data!$F:$F,MATCH($B28,Data!$B:$B,0)),0) | R28: =SUMIFS('T bills'!$M:$M,'T bills'!$D:$D,$B28,'T bills'!$E:$E,"USD",'T bills'!$A:$A,"*Treasury Bills*") | S28: =SUMIFS('T bills'!$M:$M,'T bills'!$D:$D,$B28,'T bills'!$E:$E,"EUR",'T bills'!$A:$A,"*Treasury Bills*")*$F$3 | T28: =SUM(Q28:S28)
A29: Alemagna, Tancredi Luigi | B29: 1619782 | C29: EUR | D29: =SUMIFS(#REF!,#REF!,$B29,#REF!,#REF!) | G29: =#REF!/$F$5 | H29: =MROUND(G29,1)*$F$5 | I29: =IFERROR(H29/INDEX(Data!$E:$E,MATCH($B29,Data!$B:$B,0)),0) | J29: =SUMIFS(#REF!,#REF!,$B29,#REF!,#REF!) | K29: =#REF! | M29: =#REF!/$L$5 | N29: =MROUND(M29,1)*$L$5 | O29: =IFERROR(N29/INDEX(Data!$E:$E,MATCH($B29,Data!$B:$B,0)),0) | Q29: =IFERROR(INDEX(Data!$F:$F,MATCH($B29,Data!$B:$B,0)),0) | R29: =SUMIFS('T bills'!$M:$M,'T bills'!$D:$D,$B29,'T bills'!$E:$E,"USD",'T bills'!$A:$A,"*Treasury Bills*") | S29: =SUMIFS('T bills'!$M:$M,'T bills'!$D:$D,$B29,'T bills'!$E:$E,"EUR",'T bills'!$A:$A,"*Treasury Bills*")*$F$3 | T29: =SUM(Q29:S29)
... A31: Saira Holding S.r.L. | B31: 1690341 | C31: EUR | D31: =SUMIFS(#REF!,#REF!,$B31,#REF!,#REF!) | G31: =#REF!/$F$5 | H31: =MROUND(G31,1)*$F$5 | I31: =IFERROR(H31/INDEX(Data!$E:$E,MATCH($B31,Data!$B:$B,0)),0) | J31: =SUMIFS(#REF!,#REF!,$B31,#REF!,#REF!) | K31: =#REF! | M31: =#REF!/$L$5 | N31: =MROUND(M31,1)*$L$5 | O31: =IFERROR(N31/INDEX(Data!$E:$E,MATCH($B31,Data!$B:$B,0)),0) | Q31: =IFERROR(INDEX(Data!$F:$F,MATCH($B31,Data!$B:$B,0)),0) | R31: =SUMIFS('T bills'!$M:$M,'T bills'!$D:$D,$B31,'T bills'!$E:$E,"USD",'T bills'!$A:$A,"*Treasury Bills*") | S31: =SUMIFS('T bills'!$M:$M,'T bills'!$D:$D,$B31,'T bills'!$E:$E,"EUR",'T bills'!$A:$A,"*Treasury Bills*")*$F$3 | T31: =SUM(Q31:S31)
A32: Conservative Mandate
A33: Malerba, Maria Clara | B33: 1632673 | C33: EUR | D33: =SUMIFS(#REF!,#REF!,$B33,#REF!,#REF!) | G33: =#REF!/$F$5 | H33: =MROUND(G33,1)*$F$5 | I33: =IFERROR(H33/INDEX(Data!$E:$E,MATCH($B33,Data!$B:$B,0)),0) | J33: =SUMIFS(#REF!,#REF!,$B33,#REF!,#REF!) | K33: =#REF! | M33: =#REF!/$L$5 | N33: =MROUND(M33,1)*$L$5 | O33: =IFERROR(N33/INDEX(Data!$E:$E,MATCH($B33,Data!$B:$B,0)),0) | Q33: =IFERROR(INDEX(Data!$F:$F,MATCH($B33,Data!$B:$B,0)),0) | R33: =SUMIFS('T bills'!$M:$M,'T bills'!$D:$D,$B33,'T bills'!$E:$E,"USD",'T bills'!$A:$A,"*Treasury Bills*") | S33: =SUMIFS('T bills'!$M:$M,'T bills'!$D:$D,$B33,'T bills'!$E:$E,"EUR",'T bills'!$A:$A,"*Treasury Bills*")*$F$3 | T33: =SUM(Q33:S33)
A34: Other (not on client list)
A35: Lettieri, Umberto | B35: 1710712 | C35: USD | D35: =SUMIFS(#REF!,#REF!,$B35,#REF!,#REF!) | G35: =#REF!/$F$5 | H35: =MROUND(G35,1)*$F$5 | I35: =IFERROR(H35/INDEX(Data!$E:$E,MATCH($B35,Data!$B:$B,0)),0) | J35: =SUMIFS(#REF!,#REF!,$B35,#REF!,#REF!) | K35: =#REF! | M35: =#REF!/$L$5 | N35: =MROUND(M35,1)*$L$5 | O35: =IFERROR(N35/INDEX(Data!$E:$E,MATCH($B35,Data!$B:$B,0)),0) | Q35: =IFERROR(INDEX(Data!$F:$F,MATCH($B35,Data!$B:$B,0)),0) | R35: =SUMIFS('T bills'!$M:$M,'T bills'!$D:$D,$B35,'T bills'!$E:$E,"USD",'T bills'!$A:$A,"*Treasury Bills*") | S35: =SUMIFS('T bills'!$M:$M,'T bills'!$D:$D,$B35,'T bills'!$E:$E,"EUR",'T bills'!$A:$A,"*Treasury Bills*")*$F$3 | T35: =SUM(Q35:S35)
